<Frankenstein xmlns:xhtml="http://www.w3.org/1999/xhtml">
	<part code="acquaint"/>
			<part code="actuated"/>
			<part code="adfrench"/>
			<part code="affect"/>
			<part code="againvow"/>
			<part code="agony"/>
			<part code="allowed"/>
			<part code="almost"/>
			<part code="almostas"/>
			<part code="alone"/>
			<part code="aneye"/>
			<part code="anguish"/>
			<part code="apoplex"/>
			<part code="appallin"/>
			<part code="appear"/>
			<part code="apple"/>
			<part code="archangl"/>
			<part code="ardcrave"/>
			<part code="ardesire"/>
			<part code="ardour"/>
			<part code="ardpray"/>
			<part code="ascfate"/>
			<part code="assign"/>
			<part code="assizes"/>
			<part code="atlantic"/>
			<part code="august"/>
			<part code="august26"/>
			<part code="avert"/>
			<part code="avoided"/>
			<part code="award"/>
			<part code="badcons"/>
			<part code="bealone"/>
			<part code="beautnat"/>
			<part code="bemen"/>
			<part code="benefact"/>
			<part code="bernwell"/>
			<part code="besteady"/>
			<part code="blackmel"/>
			<part code="blasted"/>
			<part code="blastmis"/>
			<part code="bluelake"/>
			<part code="bluemed"/>
			<part code="blueseas"/>
			<part code="bourne"/>
			<part code="burngush"/>
			<part code="burning"/>
			<part code="callmad"/>
			<part code="callmyse"/>
			<part code="candour"/>
			<part code="careless"/>
			<part code="castle"/>
			<part code="cemetery"/>
			<part code="claims"/>
			<part code="cloud"/>
			<part code="cologny"/>
			<part code="colonise"/>
			<part code="comcrime"/>
			<part code="comeon"/>
			<part code="command"/>
			<part code="compass"/>
			<part code="compose"/>
			<part code="comrades"/>
			<part code="conceal"/>
			<part code="conscien"/>
			<part code="continu"/>
			<part code="correct"/>
			<part code="counten"/>
			<part code="courage"/>
			<part code="courage2"/>
			<part code="creator"/>
			<part code="crimjudg"/>
			<part code="ctown"/>
			<part code="cumber"/>
			<part code="curiocom"/>
			<part code="curios"/>
			<part code="curshell"/>
			<part code="daemon"/>
			<part code="daemon2"/>
			<part code="daemon3"/>
			<part code="danger"/>
			<part code="delusion"/>
			<part code="desbarb"/>
			<part code="deserts"/>
			<part code="design"/>
			<part code="destined"/>
			<part code="detail"/>
			<part code="devil"/>
			<part code="devpass"/>
			<part code="diecast"/>
			<part code="disapp"/>
			<part code="domcalm"/>
			<part code="domestic"/>
			<part code="drag"/>
			<part code="Drance"/>
			<part code="dread"/>
			<part code="dreaming"/>
			<part code="duties"/>
			<part code="duty"/>
			<part code="dutymag"/>
			<part code="earlymar"/>
			<part code="elevmad"/>
			<part code="eloquen2"/>
			<part code="eloquen3"/>
			<part code="eloquenc"/>
			<part code="eloquent"/>
			<part code="endeav"/>
			<part code="enemy"/>
			<part code="engphil"/>
			<part code="ernest"/>
			<part code="ernlive"/>
			<part code="events"/>
			<part code="everlast"/>
			<part code="everywhr"/>
			<part code="evian"/>
			<part code="evilgood"/>
			<part code="examin"/>
			<part code="excite"/>
			<part code="extnat"/>
			<part code="fairy"/>
			<part code="falkland"/>
			<part code="family"/>
			<part code="favplan"/>
			<part code="feelings"/>
			<part code="fellow"/>
			<part code="feltsuff"/>
			<part code="fever"/>
			<part code="fever2"/>
			<part code="feverish"/>
			<part code="fiend"/>
			<part code="fiendbar"/>
			<part code="filled"/>
			<part code="filthy"/>
			<part code="fisher"/>
			<part code="fit"/>
			<part code="flying"/>
			<part code="formself"/>
			<part code="freechoi"/>
			<part code="frenzy"/>
			<part code="friend"/>
			<part code="friendsh"/>
			<part code="fulfill"/>
			<part code="fury"/>
			<part code="generous"/>
			<part code="genial"/>
			<part code="ghastly"/>
			<part code="gigantic"/>
			<part code="giving"/>
			<part code="glimmer"/>
			<part code="glorious"/>
			<part code="gnashed"/>
			<part code="gower"/>
			<part code="greeks"/>
			<part code="grin"/>
			<part code="ground"/>
			<part code="ground2"/>
			<part code="grtcrime"/>
			<part code="grtroad"/>
			<part code="guidspir"/>
			<part code="hadmoney"/>
			<part code="halfkind"/>
			<part code="harmony"/>
			<part code="havre"/>
			<part code="heart"/>
			<part code="heartbnd"/>
			<part code="hellish"/>
			<part code="hidnar"/>
			<part code="highdest"/>
			<part code="highland"/>
			<part code="hirenurs"/>
			<part code="holyhead"/>
			<part code="honour"/>
			<part code="horpilg"/>
			<part code="hour"/>
			<part code="hover"/>
			<part code="howhappy"/>
			<part code="howl"/>
			<part code="howlit"/>
			<part code="howmany"/>
			<part code="humsymp"/>
			<part code="husband"/>
			<part code="icalled"/>
			<part code="icould"/>
			<part code="icurbed"/>
			<part code="ignorant"/>
			<part code="ihadconv"/>
			<part code="imagdred"/>
			<part code="imagin"/>
			<part code="imaginat"/>
			<part code="immersol"/>
			<part code="impulses"/>
			<part code="inherit"/>
			<part code="injust"/>
			<part code="inquiry"/>
			<part code="instdart"/>
			<part code="interest"/>
			<part code="irish"/>
			<part code="irksome"/>
			<part code="isis"/>
			<part code="itwashe"/>
			<part code="iwillnot"/>
			<part code="journal"/>
			<part code="jura"/>
			<part code="justice"/>
			<part code="lakes"/>
			<part code="landscap"/>
			<part code="language"/>
			<part code="lastaut"/>
			<part code="laudanum"/>
			<part code="lead"/>
			<part code="lessons"/>
			<part code="letters"/>
			<part code="liberty"/>
			<part code="lifeext"/>
			<part code="light"/>
			<part code="listles2"/>
			<part code="listless"/>
			<part code="lost"/>
			<part code="loveanot"/>
			<part code="mad"/>
			<part code="mad2"/>
			<part code="madenthu"/>
			<part code="madrage"/>
			<part code="madschem"/>
			<part code="magist"/>
			<part code="mainland"/>
			<part code="majestic"/>
			<part code="makewret"/>
			<part code="maladie"/>
			<part code="manes"/>
			<part code="markfing"/>
			<part code="martyrs"/>
			<part code="master"/>
			<part code="material"/>
			<part code="may8"/>
			<part code="mayence"/>
			<part code="mechanic"/>
			<part code="melanch"/>
			<part code="memory"/>
			<part code="midnight"/>
			<part code="minister"/>
			<part code="miser"/>
			<part code="miserabl"/>
			<part code="mispent"/>
			<part code="miswret"/>
			<part code="miswrtch"/>
			<part code="modelled"/>
			<part code="monsdaem"/>
			<part code="monster"/>
			<part code="monster2"/>
			<part code="moondisk"/>
			<part code="morethan"/>
			<part code="morning"/>
			<part code="mostdist"/>
			<part code="mostmis"/>
			<part code="muscle"/>
			<part code="mutilate"/>
			<part code="mutiny"/>
			<part code="mychains"/>
			<part code="mydest"/>
			<part code="mydestin"/>
			<part code="myduties"/>
			<part code="myeyes"/>
			<part code="myfiend"/>
			<part code="myfriend"/>
			<part code="mygrave"/>
			<part code="myhands"/>
			<part code="myimag"/>
			<part code="myletter"/>
			<part code="mymis"/>
			<part code="myvow"/>
			<part code="mywander"/>
			<part code="mywretch"/>
			<part code="nature"/>
			<part code="nearyear"/>
			<part code="neck"/>
			<part code="newdear"/>
			<part code="newtown"/>
			<part code="nicer"/>
			<part code="night"/>
			<part code="nochoice"/>
			<part code="nocreat"/>
			<part code="nopeace"/>
			<part code="north"/>
			<part code="northern"/>
			<part code="notcred"/>
			<part code="nothear"/>
			<part code="notmad"/>
			<part code="nugent"/>
			<part code="offspring"/>
			<part code="orkney"/>
			<part code="ourcirc"/>
			<part code="outcast"/>
			<part code="particip"/>
			<part code="passion"/>
			<part code="peasant"/>
			<part code="perfsol"/>
			<part code="period"/>
			<part code="perished"/>
			<part code="person"/>
			<part code="perth"/>
			<part code="physiog"/>
			<part code="plans"/>
			<part code="poisoned"/>
			<part code="portsmou"/>
			<part code="post"/>
			<part code="power"/>
			<part code="precaut"/>
			<part code="prison"/>
			<part code="proceed"/>
			<part code="projector"/>
			<part code="promise"/>
			<part code="putanend"/>
			<part code="queen"/>
			<part code="race"/>
			<part code="race2"/>
			<part code="rage"/>
			<part code="realinsa"/>
			<part code="reality"/>
			<part code="reason"/>
			<part code="recollec"/>
			<part code="record"/>
			<part code="regret"/>
			<part code="remalone"/>
			<part code="remembra"/>
			<part code="remorse"/>
			<part code="repulsiv"/>
			<part code="resolute"/>
			<part code="restless"/>
			<part code="restrain"/>
			<part code="restspec"/>
			<part code="revenge"/>
			<part code="rimini"/>
			<part code="roarings"/>
			<part code="rotterdm"/>
			<part code="sacrific"/>
			<part code="saleve"/>
			<part code="sameboat"/>
			<part code="scene"/>
			<part code="scent"/>
			<part code="selfish"/>
			<part code="seneca"/>
			<part code="sensibil"/>
			<part code="sentence"/>
			<part code="sept2"/>
			<part code="sept9th"/>
			<part code="septemb"/>
			<part code="shadow"/>
			<part code="shout"/>
			<part code="shuteyes"/>
			<part code="single"/>
			<part code="sister"/>
			<part code="slavenot"/>
			<part code="slaveof"/>
			<part code="slavery"/>
			<part code="smooth"/>
			<part code="smother"/>
			<part code="solitude"/>
			<part code="somedest"/>
			<part code="somerev"/>
			<part code="soonlost"/>
			<part code="sounfeel"/>
			<part code="spirdead"/>
			<part code="spirgood"/>
			<part code="spirguar"/>
			<part code="spirinvo"/>
			<part code="spirit"/>
			<part code="spirits"/>
			<part code="spokenat"/>
			<part code="standrew"/>
			<part code="steeples"/>
			<part code="storm"/>
			<part code="story"/>
			<part code="stpauls"/>
			<part code="strasbrg"/>
			<part code="strchanc"/>
			<part code="struggle"/>
			<part code="subsist"/>
			<part code="succeed"/>
			<part code="sufblunt"/>
			<part code="suffic"/>
			<part code="summoney"/>
			<part code="sunshone"/>
			<part code="swear"/>
			<part code="sympath"/>
			<part code="sympstra"/>
			<part code="teargush"/>
			<part code="tears"/>
			<part code="template"/>
			<part code="thames"/>
			<part code="thatclas"/>
			<part code="thedevil"/>
			<part code="thensafe"/>
			<part code="thetower"/>
			<part code="thinner"/>
			<part code="thisdep"/>
			<part code="thrust"/>
			<part code="tilbury"/>
			<part code="tintern"/>
			<part code="tocease"/>
			<part code="torch"/>
			<part code="tore"/>
			<part code="torture"/>
			<part code="tourscot"/>
			<part code="toyou"/>
			<part code="trembled"/>
			<part code="tremblin"/>
			<part code="truereas"/>
			<part code="trytocon"/>
			<part code="turning"/>
			<part code="twomonth"/>
			<part code="unavoid"/>
			<part code="unming"/>
			<part code="uttercar"/>
			<part code="vasthand"/>
			<part code="vintage"/>
			<part code="virtue"/>
			<part code="voluntar"/>
			<part code="wasalone"/>
			<part code="watery"/>
			<part code="wearing"/>
			<part code="wept"/>
			<part code="whatfeel"/>
			<part code="whofear"/>
			<part code="wildimag"/>
			<part code="wind"/>
			<part code="windsor"/>
			<part code="windstre"/>
			<part code="wish"/>
			<part code="wretch"/>
			<part code="wretch2"/>
			<part code="yearago"/>
			<part code="youmy"/>
			<part code="young"/>
</Frankenstein>
