<?xml version="1.0" encoding="UTF-8"?>
<Edition xmlns:tei="http://www.tei-c.org/ns/1.0">
    <part code="praxis.2016.contemporary.intro.xml"/>
    <part code="praxis.2016.contemporary.lisiecki.xml"/>
    <part code="praxis.2016.contemporary.keen.xml"/>
    <part code="praxis.2016.contemporary.jokic.xml"/>
    <part code="praxis.2016.contemporary.ruderman.xml"/>
    <part code="praxis.2016.contemporary.hershinow.xml"/>
    <part code="praxis.2016.contemporary.haigwood.xml"/>
    <part code="praxis.2016.contemporary.feder.xml"/>
    <part code="praxis.2016.contemporary.dinter-john.xml"/>
    <part code="praxis.2016.contemporary.block.xml"/>
    <part code="praxis.2016.contemporary.appendix-ruderman.xml"/>
    <part code="praxis.2016.contemporary.appendix-jokic.xml"/>
    <part code="praxis.2016.contemporary.appendix-dinter-john.xml"/>
</Edition>
